<?xml version="1.0" encoding="UTF-8"?>
<databaseChangeLog xmlns="http://www.liquibase.org/xml/ns/dbchangelog"
                   xmlns:xsi="http://www.w3.org/2001/XMLSchema-instance"
                   xsi:schemaLocation="http://www.liquibase.org/xml/ns/dbchangelog
http://www.liquibase.org/xml/ns/dbchangelog/dbchangelog-4.1.xsd">

    <changeSet id="20250120125648" author="ahmedyasser">
        <insert tableName="configuration">
            <column name="key" value="organizationBotCannotAnswerAskToForwardToCSA"/>
            <column name="value" value="true"/>
        </insert>
        <insert tableName="configuration">
            <column name="key" value="organizationBotCannotAnswerMessage"/>
            <column name="value" value="Kahjuks ei oska ma hetkel teie küsimusele vastata. Kas soovite, et suunan küsimuse nõustajale?"/>
        </insert>
    </changeSet>
</databaseChangeLog>
